mfcrypt/__init__.py
mfcrypt/__version__.py
mfcrypt/mfcrypt.py
mfcrypt-0.0.7.dist-info/LICENSE
mfcrypt-0.0.7.dist-info/METADATA
mfcrypt-0.0.7.dist-info/WHEEL
mfcrypt-0.0.7.dist-info/top_level.txt
mfcrypt-0.0.7.dist-info/RECORD
