Metadata-Version: 2.1
Name: mfcrypt
Version: 0.0.7
Summary: Cryptographic utilities for Musicfox Python applications.
Home-page: https://github.com/musicfox/cryptography/
Author: Jason R. Stevens, CFA on behalf of Musicfox, Inc.
Author-email: dev@musicfox.io
License: MIT
Platform: UNKNOWN
Requires-Python: >=3.9
License-File: LICENSE
Requires-Dist: pycryptodomex
